wrapper_kafka/__init__.py
wrapper_kafka/data_helpers.py
wrapper_kafka/data_types.py
wrapper_kafka/event_types.py
wrapper_kafka/kafka_consumer.py
wrapper_kafka/kafka_producer.py
wrapper_kafka/logger.py
wrapper_kafka/prometheus.py
wrapper_kafka/testing/__init__.py
wrapper_kafka/testing/integration/__init__.py
wrapper_kafka/testing/integration/test_service_model.py
wrapper_kafka/testing/unit/__init__.py
wrapper_kafka/testing/unit/test_data_helpers.py
wrapper_kafka/testing/unit/test_data_types.py
wrapper_kafka/testing/unit/test_event_types.py
wrapper_kafka/testing/unit/test_kafka_consumer.py
wrapper_kafka/testing/unit/test_kafka_producer.py
wrapper_kafka/testing/unit/test_wrappers_prometheus.py
wrapper_kafka-0.0.4.dist-info/LICENSE.TXT
wrapper_kafka-0.0.4.dist-info/METADATA
wrapper_kafka-0.0.4.dist-info/WHEEL
wrapper_kafka-0.0.4.dist-info/top_level.txt
wrapper_kafka-0.0.4.dist-info/RECORD
