Metadata-Version: 2.1
Name: wrapper-kafka
Version: 0.0.4
Summary: Wrapper around python-kafka with pydantic serialization and prometheus-client monitoring for easy prod implementation
Home-page: UNKNOWN
Author: Pavel Tiurin
Author-email: pavel.tyurin@veeam.com
License: MIT
Platform: UNKNOWN
Classifier: License :: OSI Approved :: MIT License
Classifier: Programming Language :: Python :: 3.10
Classifier: Operating System :: OS Independent
Requires-Python: >=3.8
License-File: LICENSE.TXT
Requires-Dist: kafka-python (==2.0.2)
Requires-Dist: prometheus-client (==0.17.1)
Requires-Dist: pydantic (==2.4.2)
